protocol_gateway.py
python_protocol_gateway-1.1.10.dist-info/licenses/LICENSE
python_protocol_gateway-1.1.10.dist-info/METADATA
python_protocol_gateway-1.1.10.dist-info/WHEEL
python_protocol_gateway-1.1.10.dist-info/entry_points.txt
python_protocol_gateway-1.1.10.dist-info/top_level.txt
python_protocol_gateway-1.1.10.dist-info/RECORD
