Metadata-Version: 2.4
Name: python-protocol-gateway
Version: 1.1.10
Summary: Python Protocol Gateway reads data via Modbus RTU or other protocols and translates the data for MQTT. In the long run, Python Protocol Gateway will become a general purpose protocol gateway to translate between more than just modbus and mqtt.
Author-email: HotNoob <hotnoob@hotnoob.com>
License-Expression: Apache-2.0
Project-URL: Homepage, https://github.com/HotNoob/PythonProtocolGateway
Project-URL: Repository, https://github.com/HotNoob/PythonProtocolGateway
Requires-Python: >=3.9
License-File: LICENSE
Requires-Dist: pymodbus==3.7.0
Requires-Dist: paho-mqtt
Requires-Dist: pyserial
Requires-Dist: python-can
Requires-Dist: influxdb
Provides-Extra: dev
Requires-Dist: ruff; extra == "dev"
Requires-Dist: modbus_tk; extra == "dev"
Requires-Dist: pytest; extra == "dev"
Dynamic: license-file
